LICENSE
README.md
setup.py
OlivOS/__init__.py
OlivOS/hook.py
OlivOS/hook_pack.py
OlivOS/hook_pack_debug.py
OlivOS/thirdPartyModule/__init__.py
OlivOS/thirdPartyModule/blivedm/__init__.py
OlivOS/thirdPartyModule/blivedm/client.py
OlivOS/thirdPartyModule/blivedm/handlers.py
OlivOS/thirdPartyModule/blivedm/models.py
OlivOS/thirdPartyModule/mhyVilaProto/__init__.py
OlivOS/thirdPartyModule/mhyVilaProto/command_pb2.py
OlivOS/thirdPartyModule/mhyVilaProto/model_pb2.py
OlivOS/thirdPartyModule/mhyVilaProto/robot_event_message_pb2.py
OlivOS/thirdPartyModule/mhyVilaProto/tools.py
OlivOS/userModule/IOStream.py
OlivOS/userModule/JyunkoUserConf.py
OlivOS/userModule/UserConfDB.py
OlivOS/userModule/__init__.py
olivos.egg-info/PKG-INFO
olivos.egg-info/SOURCES.txt
olivos.egg-info/dependency_links.txt
olivos.egg-info/requires.txt
olivos.egg-info/top_level.txt