Metadata-Version: 2.1
Name: olivos
Version: 0.11.48
Summary: OlivOS - Witness Union
Home-page: https://github.com/OlivOS-Team/OlivOS
Author: OlivOS-Team
Author-email: lunzhipenxil@gmail.com
License: AGPLv3 License
Classifier: Operating System :: OS Independent
Classifier: License :: OSI Approved :: GNU Affero General Public License v3
Classifier: Programming Language :: Python :: 3
License-File: LICENSE
